plwidgets/PlWidgets.py
plwidgets/__init__.py
plwidgets/pl_check_button_group.py
plwidgets/pl_checkbox.py
plwidgets/pl_combo_box.py
plwidgets/pl_dialog.py
plwidgets/pl_flag.py
plwidgets/pl_form_widget.py
plwidgets/pl_line_edit.py
plwidgets/pl_loading_indicator.py
plwidgets/pl_overlay_dialog.py
plwidgets/pl_progress_circle.py
plwidgets/pl_push_button.py
plwidgets/pl_resizable_mixin.py
plwidgets/pl_round_check_button.py
plwidgets/pl_search_bar.py
plwidgets/pl_slider.py
plwidgets/pl_style_mixin.py
plwidgets/pl_tab_widget.py
plwidgets/pl_title_bar.py
plwidgets/resource_utils.py
plwidgets-0.1.1.dist-info/licenses/LICENSE
plwidgets-0.1.1.dist-info/METADATA
plwidgets-0.1.1.dist-info/WHEEL
plwidgets-0.1.1.dist-info/top_level.txt
plwidgets-0.1.1.dist-info/RECORD
