Metadata-Version: 2.4
Name: plwidgets
Version: 0.1.1
Summary: Custom PySide6 UI widgets for Python applications
Author-email: Pierre-Lou Guilloré <pl.guillore@gmail.com>
License-Expression: MIT
Project-URL: Homepage, https://github.com/ThePeterWolf/pl-widgets
Project-URL: Documentation, https://github.com/ThePeterWolf/pl-widgets#readme
Requires-Python: >=3.7
License-File: LICENSE
Requires-Dist: PySide6>=6.3
Dynamic: license-file
